[
  {
    "id": "8bedd74a14e9ef37bb89ee0f2b21e134",
    "title": "Truecaller faces mounting pressures as its growth matures",
    "summary": "As growth slows, Truecaller is leaning on subscriptions, business services, and new features to sust",
    "url": "https://techcrunch.com/2026/04/26/truecaller-faces-mounting-pressures-as-its-growth-matures/",
    "source": "TechCrunch",
    "published": "Mon, 27 Apr 2026 03:00:00 +0000",
    "category": "tech",
    "importance": 3,
    "why_read": "Interesting read"
  },
  {
    "id": "358379584c65450df2a2556d36b736c5",
    "title": "The Stanford freshmen who want to rule the world . . . will probably read this book and try even harder",
    "summary": "Can a book like this actually change anything? Or does the spotlight, as it always seems to, send mo",
    "url": "https://techcrunch.com/2026/04/26/the-stanford-freshmen-who-want-to-rule-the-world-will-probably-read-this-book-and-try-even-harder/",
    "source": "TechCrunch",
    "published": "Sun, 26 Apr 2026 22:00:46 +0000",
    "category": "tech",
    "importance": 3,
    "why_read": "Interesting read"
  },
  {
    "id": "c986265591dda452b90acfbb18454bfe",
    "title": "Amazon\u2019s new podcast strategy: Monetize everything",
    "summary": "Amazon's podcasting business seems to have transformed over the past six months.",
    "url": "https://techcrunch.com/2026/04/26/amazons-new-podcast-strategy-monetize-everything/",
    "source": "TechCrunch",
    "published": "Sun, 26 Apr 2026 21:38:08 +0000",
    "category": "tech",
    "importance": 3,
    "why_read": "Interesting read"
  },
  {
    "id": "ef2ccda5e4e5ba5a0c532fed3d8fb329",
    "title": "What Tim Cook built",
    "summary": "On the latest episode of Equity, we discuss how Apple has changed since Cook became CEO in 2011, and",
    "url": "https://techcrunch.com/2026/04/26/what-tim-cook-built/",
    "source": "TechCrunch",
    "published": "Sun, 26 Apr 2026 20:22:51 +0000",
    "category": "tech",
    "importance": 3,
    "why_read": "Interesting read"
  },
  {
    "id": "f59a3eb2999a7e3d3a262b011f865ed0",
    "title": "TechCrunch Mobility: Elon\u2019s admission",
    "summary": "Welcome back to TechCrunch Mobility \u2014 your central hub for news and insights on the future of transp",
    "url": "https://techcrunch.com/2026/04/26/techcrunch-mobility-elons-admission/",
    "source": "TechCrunch",
    "published": "Sun, 26 Apr 2026 16:03:00 +0000",
    "category": "tech",
    "importance": 3,
    "why_read": "Interesting read"
  },
  {
    "id": "705b64961b83af2bfe1c69a61cab38c5",
    "title": "Google\u2019s new gradient icon design is coming to more apps",
    "summary": "In late 2025, Google started rolling out new icons with a gradient design. Now it seems the new look",
    "url": "https://www.theverge.com/tech/918852/googles-new-gradient-icon-design-is-coming-to-more-apps",
    "source": "The Verge",
    "published": "2026-04-26T14:34:26-04:00",
    "category": "tech",
    "importance": 3,
    "why_read": "Interesting read"
  },
  {
    "id": "ccb03a175a3da046d2c33f55e472f621",
    "title": "Trump turns the WHCD shooting into a pitch for the White House ballroom",
    "summary": "Within hours of an armed gunman's attempt to enter the White House Correspondents Dinner, attended b",
    "url": "https://www.theverge.com/policy/918843/trump-whcd-attack-white-house-ballroom",
    "source": "The Verge",
    "published": "2026-04-26T12:18:02-04:00",
    "category": "tech",
    "importance": 3,
    "why_read": "Interesting read"
  },
  {
    "id": "ab7295d0b73cedeeefd2b258991f4ac3",
    "title": "Tomora\u2019s Come Closer is an ecstatic love letter to 90s dance music",
    "summary": "Before Coachella, Tomora wasn't on my radar at all. It's actually only by chance that I stumbled upo",
    "url": "https://www.theverge.com/entertainment/918826/tomora-come-closer-review-90s-dance-music",
    "source": "The Verge",
    "published": "2026-04-26T12:00:00-04:00",
    "category": "tech",
    "importance": 3,
    "why_read": "Interesting read"
  },
  {
    "id": "4446137317bfef2205c16431d4204441",
    "title": "Skylight\u2019s 15-inch smart calendar is down to its lowest price to date",
    "summary": "When you\u2019re juggling more than just your own calendar, staying organized can be overwhelming. Fortun",
    "url": "https://www.theverge.com/gadgets/918544/skylight-15-inch-smart-calendar-2-mothers-day-deal-2026-sale",
    "source": "The Verge",
    "published": "2026-04-26T10:05:03-04:00",
    "category": "tech",
    "importance": 3,
    "why_read": "Interesting read"
  },
  {
    "id": "fcbdbbb26eacecc36e16f19164194c7f",
    "title": "After three months on Linux, I don\u2019t miss Windows at all",
    "summary": "In January I finally made good on my threat/promise to install Linux on my desktop. I wanted to see ",
    "url": "https://www.theverge.com/tech/918797/switched-to-linux-dont-miss-windows",
    "source": "The Verge",
    "published": "2026-04-26T09:00:00-04:00",
    "category": "tech",
    "importance": 3,
    "why_read": "Interesting read"
  },
  {
    "id": "13d484eb31e3f4dc98e8e4e509ea2bfa",
    "title": "Entire NSF science advisory board fired by Trump administration",
    "summary": "<p>Nature, Published online: 26 April 2026; <a href=\"https://www.nature.com/articles/d41586-026-0136",
    "url": "https://www.nature.com/articles/d41586-026-01361-7",
    "source": "Nature",
    "published": "",
    "category": "science",
    "importance": 3,
    "why_read": "Interesting read"
  },
  {
    "id": "ab87ac98281dde296344caad89b398dc",
    "title": "Author Correction: Commensal yeast promotes <i>Salmonella</i> Typhimurium virulence",
    "summary": "<p>Nature, Published online: 24 April 2026; <a href=\"https://www.nature.com/articles/s41586-026-1051",
    "url": "https://www.nature.com/articles/s41586-026-10518-3",
    "source": "Nature",
    "published": "",
    "category": "science",
    "importance": 3,
    "why_read": "Interesting read"
  },
  {
    "id": "133eac928606b26e1af278632e6c9178",
    "title": "Author Correction: A \u00b5-opioid receptor superagonist analgesic with minimal adverse effects",
    "summary": "<p>Nature, Published online: 24 April 2026; <a href=\"https://www.nature.com/articles/s41586-026-1055",
    "url": "https://www.nature.com/articles/s41586-026-10552-1",
    "source": "Nature",
    "published": "",
    "category": "science",
    "importance": 3,
    "why_read": "Interesting read"
  },
  {
    "id": "04db7dd2fe7237aae77446a13026606d",
    "title": "Cosmic-ray detection heralds era of mega-observatories for neutrinos",
    "summary": "<p>Nature, Published online: 24 April 2026; <a href=\"https://www.nature.com/articles/d41586-026-0128",
    "url": "https://www.nature.com/articles/d41586-026-01282-5",
    "source": "Nature",
    "published": "",
    "category": "science",
    "importance": 3,
    "why_read": "Interesting read"
  },
  {
    "id": "e1485385595c4a6d365844c604bb9b7e",
    "title": "From bats at dusk to asteroid quests: Books in brief",
    "summary": "<p>Nature, Published online: 24 April 2026; <a href=\"https://www.nature.com/articles/d41586-026-0130",
    "url": "https://www.nature.com/articles/d41586-026-01304-2",
    "source": "Nature",
    "published": "",
    "category": "science",
    "importance": 3,
    "why_read": "Interesting read"
  }
]